{"Nm0g4VkzxduI/Y5hXUyYHQ==":"mbr-1920x1280.jpg","S/XTDaYQVzRYliKrHKORhw==":"eztraining%20business%20card-900x514.png","bMg0iQcXa/ZDUeB2tjApPQ==":"eztraining%20business%20card-900x514.png","pVI1WjgDxp5Jd72t02b82g==":"bannedapps.uk-900x514.png","t9GjZL7Ms+5k8oSN8YBkCg==":"untitled%20design-900x514.png","459l/LFnCZ7i82BrDoshpA==":"cara-mia's%20reviews-900x514.png","35pJhWSy828MudrKBHQFeQ==":"kayla's%20piercings-500x500.png","Jtq2nK0S3jvRP9fsKvyHFQ==":"1606870552508-671x387.jpg","9/ob2WVeXhnBFl8rSWZ1aQ==":"capture-696x319.png","8nx9xFkLKrO+XJ9ZOr9YXQ==":"capture-1-696x319.png","LH53ISg57iyuB+nOl8B2OA==":"capture-2-696x319.png","oCu4BzPQT7pTWrZ2Eb0axg==":"download-696x364.png","WiDzIfBPS0QZJhR9qz1TYg==":"89d22a27b4fc9b70d2a6c78148b267c2-900x444.png","6Ip8CIJSZGkAk3U1LqZJcA==":"89d22a27b4fc9b70d2a6c78148b267c2-506x250.png","Gs/B7Ki/+n0hkJbOuFuR+w==":"capture-696x323.png","SQ5cKW3WsRoWeOIWeyDDOg==":"capture-1-696x323.png","eioPwbwwQO4Wt5nzYmP+tw==":"mbr-1920x1080.jpg","BqO+5KrheXdAh1rzgojdCA==":"2-1050x600.png","8h2yiNjCSPFntlP8JLP0IA==":"niwebdesigns-1050x600.png","/KwSBASKqSXeI+mSy1fweg==":"niwebdesigns-900x514.png","rqwO4+XbBFRAM39PUoI1UQ==":"capture-696x324.png","6ZVNIeK+7I1Sli0D3mxiGA==":"mbr-1920x1167.jpg","xvWnJRndE/oEd7y8IRmtZw==":"mbr-1920x1357.jpg","5lxKFK8bTVrIP/9L8MG2tA==":"background2.jpg","b5zlcTRn6Wu5rg/V5S3HLQ==":"mbr-1920x1257.jpg","E4OuT9JbzGFANrI/5eaoDA==":"capture-696x345.png","vS5UZmukD1TzfXCgSztLWQ==":"ubiygy-696x344.png","7U/2b9a2PuqwdDk+t3YT/A==":"dfbdfbdfbdf-1904x940.png","gGL6prdszWLAm28B9RlXSA==":"ubiygy-1894x935.png","d0ubDYEorsepwyTOQH4ePg==":"background4-1.jpg","EgDo+CZrLOU1/lv5gWNd3w==":"02-1.jpg","Shy099DGYtaGQX4HLLRnhw==":"03-1.jpg","NKz4Rzqsh1qpZbkGtUxy8Q==":"01-1.jpg","0po8VM3iWa40C1TiTSS01g==":"mothers%20day-900x754.png","DCfex3yVADrHUTbhzlOiwQ==":"11-900x900.png","9mtxe4zq5HfBcJMZnacjwQ==":"11-696x696.png","VQ0DMoFKZpuxqS4b+JyL5Q==":"mothers%20day-696x583.png","JDbwzkUCizo4LwBQTfCYWA==":"mothers%20day-696x583.png","upqGlYqBX5kuPyo/Gf9bNg==":"mothers%20day-696x583.png","K8v8rVN+Sp6jBvyWRF+jvw==":"mothers%20day-940x788.png","4pefMwvHDuUMh+VC9WBgug==":"11-1080x1080.png","hum4YsiJeQW1CUM5K0xZvQ==":"11-940x940.png","tQWm1yiPHGF/D1x8P7SueA==":"1612531326487-696x696.jpg","HK/d9WiktxENwYAtu6y/xA==":"air_phone_front_nocard_amex_pin_chip_2019_uk-872x872.png","95dvWBirg2F9Uu4BwPbRfg==":"30-20-3g-alone-front-nocard-sumupname-stand-2019-hr-640x640.png","8NCNSOsteu36JAGMn3hZSw==":"36-cradle-air-perspective-2019-1629x1629.png","Ay/UXaI8sGGqcw6DeYusWQ==":"34-3g-printer-mbp-9808-alone-perspective-reciept-1629x1560.jpg","swG6Lx5z+Pyvj/o+CeChNg==":"36-cradle-air-perspective-2019-872x872.png","ZsmvRGnxQc0A6vzRpcnY1A==":"36-cradle-air-perspective-2020-872x872.png","2TNdaQgcb8kUfX42GxL7xA==":"air_phone_front_nocard_amex_pin_chip_2019_uk-1-872x872.png","ObuligUop4wq0t6KdUnR7Q==":"air-phone-front-nocard-amex-pin-chip-2019-uk.png","tPDf4v0uQHiPTgEghpA1pQ==":"36-cradle-air-perspective-2019.png","RtvCVML5wvqaaC8i5qjSUA==":"30-20-3g-alone-front-nocard-sumupname-stand-2019-hr.png","XP2FLVe3ilkg7mpjxyz/0Q==":"34-3g-printer-mbp-9808-alone-perspective-reciept.jpg","fTf70MUPaMfI8acMY+BoAA==":"3g_printer_mbp_9808_alone_perspective_reciept-872x643.png","BFUKq2zsF00ujWgVsUtGXQ==":"3g_printer_mbp_9808_alone_perspective_reciept-1-872x643.png","43VHiCC03TcJgDJsk4cqTw==":"3g_printer_mbp_9808_alone_perspective_reciept-2-872x643.png","TQnVKRcUiBpVm619pTFm0Q==":"3g_printer_mbp_9808_alone_perspective_reciept-3-872x643.png","34MYpClDTmmcjqEwKoQ4Fg==":"34-3g-printer-mbp-9808-alone-perspective-reciept-872x835.jpg","hneJJvMY1/ysnkCC2wQAgQ==":"1612531326487-696x696.jpeg","FnLCJPYKxQAty23OtEaw+Q==":"niwebdesigns-copy-512x512.png"}